LICENSE.txt
MANIFEST.in
README.rst
setup.py
DjangoKeyhole.egg-info/PKG-INFO
DjangoKeyhole.egg-info/SOURCES.txt
DjangoKeyhole.egg-info/dependency_links.txt
DjangoKeyhole.egg-info/pbr.json
DjangoKeyhole.egg-info/top_level.txt
keyhole/__init__.py
keyhole/widgets.py
keyhole/static/keyhole/css/photo.png
keyhole/static/keyhole/css/style.css
keyhole/static/keyhole/js/jquery.cropit.js
keyhole/static/keyhole/js/main.js