Metadata-Version: 1.1
Name: DjangoKeyhole
Version: 0.7.dev0
Summary: Django form widget for cropping uploaded images based on a predefined size
Home-page: https://github.com/BontaVlad/DjangoKeyhole
Author: Bonta Sergiu Vlad
Author-email: bonta.vlad@gmail.com
License: MIT License, see LICENSE.txt
Platform: UNKNOWN
Classifier: Development Status :: 3 - Alpha
Classifier: Environment :: Web Environment
Classifier: Framework :: Django
Classifier: Intended Audience :: Developers
Classifier: Operating System :: OS Independent
Classifier: Programming Language :: Python
Classifier: Topic :: Software Development :: Libraries :: Python Modules
Classifier: Programming Language :: Python
Classifier: Programming Language :: Python :: 2.7
Classifier: Programming Language :: Python :: 3
Classifier: Programming Language :: Python :: 3.4
